yeelight_sn/__init__.py
yeelight_sn/color.py
yeelight_sn/yeelight.py
yeelight_sn/commands/__init__.py
yeelight_sn/commands/command.py
yeelight_sn/commands/get_prop.py
yeelight_sn/commands/set_brightness.py
yeelight_sn/commands/set_color.py
yeelight_sn/commands/set_color_temp.py
yeelight_sn/commands/set_power.py
yeelight_sn/network/discovery.py
yeelight_sn/network/dispatch.py
yeelight_sn-0.0.1.dist-info/METADATA
yeelight_sn-0.0.1.dist-info/WHEEL
yeelight_sn-0.0.1.dist-info/licenses/LICENSE
yeelight_sn-0.0.1.dist-info/RECORD
